{
  "index": "1969-B-3",
  "type": "ANA",
  "tag": [
    "ANA",
    "ALG",
    "NT"
  ],
  "difficulty": "",
  "question": "B-3. The terms of a sequence \\( T_{n} \\) satisfy\n\\[\nT_{n} T_{n+1}=n \\quad(n=1,2,3, \\cdots) \\text { and } \\lim _{n \\rightarrow \\infty} \\frac{T_{n}}{T_{n+1}}=1\n\\]\n\nShow that \\( \\pi T_{1}^{2}=2 \\).",
  "solution": "B-3 The first relation implies that\n\\[\n\\begin{array}{ll}\nT_{n}=\\frac{(n-1)(n-3) \\cdots 3}{(n-2)(n-4) \\cdots 2} \\cdot \\frac{1}{T_{1}} & \\text { if } n \\text { is even } \\\\\nT_{n}=\\frac{(n-1)(n-3) \\cdots 2}{(n-2)(n-4) \\cdots 1} \\cdot T_{1} & \\text { if } n \\text { is odd }\n\\end{array}\n\\]\n\nIf \\( n \\) is odd,\n\\[\n\\frac{T_{n}}{T_{n+1}}=\\left(T_{1}\\right)^{2} \\cdot \\frac{2}{1} \\frac{2}{3} \\frac{4}{3} \\frac{4}{5} \\frac{6}{5} \\cdots \\frac{(n-1)}{(n-2)} \\frac{(n-1)}{n}\n\\]\n\nThe Wallis product is \\( \\pi / 2=\\frac{22}{1} \\frac{24}{3} \\frac{4}{5} \\frac{8}{5} \\cdots \\). After an even number of factors the partial product is less than \\( \\pi / 2 \\) and after an odd number of factors the partial product is greater than \\( \\pi / 2 \\). Thus for the case when \\( n \\) is odd, \\( T_{n} / T_{n+1}<\\frac{1}{2} \\pi T_{1}^{2} \\). A similar calculation shows that, when \\( n \\) is even, \\( T_{n} / T_{n+1}<2 / \\pi T_{1}^{2} \\). Since the limit of \\( T_{n} / T_{n+1}=1,1 \\) is less than or equal to both \\( \\frac{1}{2} \\pi T_{1}^{2} \\) and its reciprocal. This implies that \\( \\pi T_{1}^{2}=2 \\).",
  "vars": [
    "T_n",
    "T_n+1",
    "n"
  ],
  "params": [
    "T_1"
  ],
  "sci_consts": [],
  "variants": {
    "descriptive_long": {
      "map": {
        "T_n": "curterm",
        "T_n+1": "nextterm",
        "n": "indexvar",
        "T_1": "firstterm"
      },
      "question": "B-3. The terms of a sequence \\( curterm \\) satisfy\n\\[\ncurterm nextterm=indexvar \\quad(indexvar=1,2,3, \\cdots) \\text { and } \\lim _{indexvar \\rightarrow \\infty} \\frac{curterm}{nextterm}=1\n\\]\n\nShow that \\( \\pi firstterm^{2}=2 \\).",
      "solution": "B-3 The first relation implies that\n\\[\n\\begin{array}{ll}\ncurterm=\\frac{(indexvar-1)(indexvar-3) \\cdots 3}{(indexvar-2)(indexvar-4) \\cdots 2} \\cdot \\frac{1}{firstterm} & \\text { if } indexvar \\text { is even } \\\\\ncurterm=\\frac{(indexvar-1)(indexvar-3) \\cdots 2}{(indexvar-2)(indexvar-4) \\cdots 1} \\cdot firstterm & \\text { if } indexvar \\text { is odd }\n\\end{array}\n\\]\n\nIf \\( indexvar \\) is odd,\n\\[\n\\frac{curterm}{nextterm}=\\left(firstterm\\right)^{2} \\cdot \\frac{2}{1} \\frac{2}{3} \\frac{4}{3} \\frac{4}{5} \\frac{6}{5} \\cdots \\frac{(indexvar-1)}{(indexvar-2)} \\frac{(indexvar-1)}{indexvar}\n\\]\n\nThe Wallis product is \\( \\pi / 2=\\frac{22}{1} \\frac{24}{3} \\frac{4}{5} \\frac{8}{5} \\cdots \\). After an even number of factors the partial product is less than \\( \\pi / 2 \\) and after an odd number of factors the partial product is greater than \\( \\pi / 2 \\). Thus for the case when \\( indexvar \\) is odd, \\( curterm / nextterm<\\frac{1}{2} \\pi firstterm^{2} \\). A similar calculation shows that, when \\( indexvar \\) is even, \\( curterm / nextterm<2 / \\pi firstterm^{2} \\). Since the limit of \\( curterm / nextterm=1,1 \\) is less than or equal to both \\( \\frac{1}{2} \\pi firstterm^{2} \\) and its reciprocal. This implies that \\( \\pi firstterm^{2}=2 \\)."
    },
    "descriptive_long_confusing": {
      "map": {
        "T_n": "lilacstone",
        "T_n+1": "crimsonleaf",
        "n": "harborwind",
        "T_1": "orchidtrail"
      },
      "question": "B-3. The terms of a sequence \\( lilacstone \\) satisfy\n\\[\nlilacstone\\, crimsonleaf=harborwind \\quad(harborwind=1,2,3, \\cdots) \\text { and } \\lim _{harborwind \\rightarrow \\infty} \\frac{lilacstone}{crimsonleaf}=1\n\\]\n\nShow that \\( \\pi orchidtrail^{2}=2 \\).",
      "solution": "B-3 The first relation implies that\n\\[\n\\begin{array}{ll}\nlilacstone=\\frac{(harborwind-1)(harborwind-3) \\cdots 3}{(harborwind-2)(harborwind-4) \\cdots 2} \\cdot \\frac{1}{orchidtrail} & \\text { if } harborwind \\text { is even } \\\\\nlilacstone=\\frac{(harborwind-1)(harborwind-3) \\cdots 2}{(harborwind-2)(harborwind-4) \\cdots 1} \\cdot orchidtrail & \\text { if } harborwind \\text { is odd }\n\\end{array}\n\\]\n\nIf \\( harborwind \\) is odd,\n\\[\n\\frac{lilacstone}{crimsonleaf}=\\left(orchidtrail\\right)^{2} \\cdot \\frac{2}{1} \\frac{2}{3} \\frac{4}{3} \\frac{4}{5} \\frac{6}{5} \\cdots \\frac{(harborwind-1)}{(harborwind-2)} \\frac{(harborwind-1)}{harborwind}\n\\]\n\nThe Wallis product is \\( \\pi / 2=\\frac{22}{1} \\frac{24}{3} \\frac{4}{5} \\frac{8}{5} \\cdots \\). After an even number of factors the partial product is less than \\( \\pi / 2 \\) and after an odd number of factors the partial product is greater than \\( \\pi / 2 \\). Thus for the case when \\( harborwind \\) is odd, \\( lilacstone / crimsonleaf<\\frac{1}{2} \\pi orchidtrail^{2} \\). A similar calculation shows that, when \\( harborwind \\) is even, \\( lilacstone / crimsonleaf<2 / \\pi orchidtrail^{2} \\). Since the limit of \\( lilacstone / crimsonleaf=1,1 \\) is less than or equal to both \\( \\frac{1}{2} \\pi orchidtrail^{2} \\) and its reciprocal. This implies that \\( \\pi orchidtrail^{2}=2 \\)."
    },
    "descriptive_long_misleading": {
      "map": {
        "T_{n}": "constantvalue",
        "T_{n+1}": "previousvalue",
        "n": "steadystate",
        "T_{1}": "lastterm"
      },
      "question": "B-3. The terms of a sequence \\( constantvalue \\) satisfy\n\\[\nconstantvalue\\,previousvalue = steadystate \\quad(steadystate=1,2,3, \\cdots) \\text { and } \\lim _{steadystate \\rightarrow \\infty} \\frac{constantvalue}{previousvalue}=1\n\\]\n\nShow that \\( \\pi lastterm^{2}=2 \\).",
      "solution": "B-3 The first relation implies that\n\\[\n\\begin{array}{ll}\nconstantvalue=\\frac{(steadystate-1)(steadystate-3) \\cdots 3}{(steadystate-2)(steadystate-4) \\cdots 2} \\cdot \\frac{1}{lastterm} & \\text { if } n \\text { is even } \\\\\nconstantvalue=\\frac{(steadystate-1)(steadystate-3) \\cdots 2}{(steadystate-2)(steadystate-4) \\cdots 1} \\cdot lastterm & \\text { if } n \\text { is odd }\n\\end{array}\n\\]\n\nIf \\( steadystate \\) is odd,\n\\[\n\\frac{constantvalue}{previousvalue}=\\left(lastterm\\right)^{2} \\cdot \\frac{2}{1} \\frac{2}{3} \\frac{4}{3} \\frac{4}{5} \\frac{6}{5} \\cdots \\frac{(steadystate-1)}{(steadystate-2)} \\frac{(steadystate-1)}{steadystate}\n\\]\n\nThe Wallis product is \\( \\pi / 2=\\frac{22}{1} \\frac{24}{3} \\frac{4}{5} \\frac{8}{5} \\cdots \\). After an even number of factors the partial product is less than \\( \\pi / 2 \\) and after an odd number of factors the partial product is greater than \\( \\pi / 2 \\). Thus for the case when \\( steadystate \\) is odd, \\( constantvalue / previousvalue<\\frac{1}{2} \\pi lastterm^{2} \\). A similar calculation shows that, when \\( steadystate \\) is even, \\( constantvalue / previousvalue<2 / \\pi lastterm^{2} \\). Since the limit of \\( constantvalue / previousvalue=1,1 \\) is less than or equal to both \\( \\frac{1}{2} \\pi lastterm^{2} \\) and its reciprocal. This implies that \\( \\pi lastterm^{2}=2 \\)."
    },
    "garbled_string": {
      "map": {
        "T_n": "qzxwvtnp",
        "T_n+1": "hjgrksla",
        "n": "blmkqtrs",
        "T_1": "vprmjzqe"
      },
      "question": "B-3. The terms of a sequence \\( qzxwvtnp \\) satisfy\n\\[\nqzxwvtnp hjgrksla=blmkqtrs \\quad(blmkqtrs=1,2,3, \\cdots) \\text { and } \\lim _{blmkqtrs \\rightarrow \\infty} \\frac{qzxwvtnp}{hjgrksla}=1\n\\]\n\nShow that \\( \\pi vprmjzqe^{2}=2 \\).",
      "solution": "B-3 The first relation implies that\n\\[\n\\begin{array}{ll}\nqzxwvtnp=\\frac{(blmkqtrs-1)(blmkqtrs-3) \\cdots 3}{(blmkqtrs-2)(blmkqtrs-4) \\cdots 2} \\cdot \\frac{1}{vprmjzqe} & \\text { if } blmkqtrs \\text { is even } \\\\\nqzxwvtnp=\\frac{(blmkqtrs-1)(blmkqtrs-3) \\cdots 2}{(blmkqtrs-2)(blmkqtrs-4) \\cdots 1} \\cdot vprmjzqe & \\text { if } blmkqtrs \\text { is odd }\n\\end{array}\n\\]\n\nIf \\( blmkqtrs \\) is odd,\n\\[\n\\frac{qzxwvtnp}{hjgrksla}=\\left(vprmjzqe\\right)^{2} \\cdot \\frac{2}{1} \\frac{2}{3} \\frac{4}{3} \\frac{4}{5} \\frac{6}{5} \\cdots \\frac{(blmkqtrs-1)}{(blmkqtrs-2)} \\frac{(blmkqtrs-1)}{blmkqtrs}\n\\]\n\nThe Wallis product is \\( \\pi / 2=\\frac{22}{1} \\frac{24}{3} \\frac{4}{5} \\frac{8}{5} \\cdots \\). After an even number of factors the partial product is less than \\( \\pi / 2 \\) and after an odd number of factors the partial product is greater than \\( \\pi / 2 \\). Thus for the case when \\( blmkqtrs \\) is odd, \\( qzxwvtnp / hjgrksla<\\frac{1}{2} \\pi vprmjzqe^{2} \\). A similar calculation shows that, when \\( blmkqtrs \\) is even, \\( qzxwvtnp / hjgrksla<2 / \\pi vprmjzqe^{2} \\). Since the limit of \\( qzxwvtnp / hjgrksla=1,1 \\) is less than or equal to both \\( \\frac{1}{2} \\pi vprmjzqe^{2} \\) and its reciprocal. This implies that \\( \\pi vprmjzqe^{2}=2 \\)."
    },
    "kernel_variant": {
      "question": "Fix a real parameter \\beta  > 0 and let (a_n)_{n\\geq 0} be a sequence of positive real numbers satisfying  \n\n (I) a_n a_{n+1} = n + \\beta    (n = 0,1,2,\\ldots ),  \n\n (II) lim_{n\\to \\infty } a_n / a_{n+1} = 1.  \n\nProve the following assertions.\n\n1.  (Square-root law) lim_{n\\to \\infty } a_n / \\sqrt{n} = 1.  \n\n2.  (Exact normalisation)   \n  a_0^2 = 2\\cdot [ \\Gamma ((\\beta +1)/2) / \\Gamma (\\beta /2) ]^2.  \n\n3.  (Full asymptotic expansion) For every m\\in \\mathbb{N} there exist polynomials P_1,\\ldots ,P_m in \\beta  with deg P_k = k such that  \n\n  a_n = \\sqrt{n} \\cdot  ( 1 + \\sum _{k=1}^{m} P_k(\\beta )/n^{k} ) + O(n^{-m-\\frac{1}{2}})  (n\\to \\infty ).  \n\n The first two polynomials are  \n  P_1(\\beta ) = \\beta /2 - 1/4,  P_2(\\beta ) = (-4\\beta ^2 + 4\\beta  + 1) / 32,  \n\n and in particular  \n\n  lim_{n\\to \\infty } n ( a_n - \\sqrt{n} ) = \\beta /2 - 1/4.\n\n(The general coefficients can be written explicitly in terms of Bernoulli numbers.)\n\n------------------------------------------------------------------------------------------------------------",
      "solution": "Throughout we fix \\beta  > 0 and assume a_n > 0.  We denote n\\to \\infty  with n\\in \\mathbb{N}.\n\n0.  Even-odd splitting  \nDefine  \n\n E_n := a_{2n},  O_n := a_{2n+1}  (n\\geq 0).\n\nFrom (I) we derive  \n\n E_nO_n = 2n+\\beta ,  O_nE_{n+1} = 2n+1+\\beta .  (\\dagger )\n\nConsequently  \n\n E_{n+1} = (2n+1+\\beta )/O_n,  O_n = (2n+\\beta )/E_n.  (\\dagger \\dagger )\n\n------------------------------------------------------------------------------------------------------------  \n1.  Closed product formulae  \nIterating (\\dagger \\dagger ) yields  \n\n E_n = a_0 \\cdot  \\prod _{j=1}^{n} (2j-1+\\beta )/(2j-2+\\beta ),  (1a)  \n\n O_n = (\\beta /a_0)\\cdot \\prod _{j=1}^{n} (2j+\\beta )/(2j-1+\\beta ).  (1b)\n\n(The case n=0 reads a_1=\\beta /a_0.)\n\n------------------------------------------------------------------------------------------------------------  \n2.  Determination of a_0  \nLet  \n\n s := (\\beta +1)/2  (so \\beta =2s-1 and s>\\frac{1}{2}).\n\nUsing the identity  \n  \\prod _{j=1}^{n}(j+\\alpha )=\\Gamma (n+1+\\alpha )/\\Gamma (1+\\alpha ),  \nformulae (1a)-(1b) become  \n\n E_n = a_0\\cdot \\Gamma (n+s)/\\Gamma (s)\\cdot \\Gamma (s-\\frac{1}{2})/\\Gamma (n+s-\\frac{1}{2}),  (2a)  \n\n O_n = (\\beta /a_0)\\cdot \\Gamma (n+s+\\frac{1}{2})/\\Gamma (s+\\frac{1}{2})\\cdot \\Gamma (s)/\\Gamma (n+s).  (2b)\n\nTaking the quotient we get  \n\n E_n/O_n = (a_0^2/\\beta ) \\cdot  \\Gamma (n+s)^2 \\Gamma (s-\\frac{1}{2})\\Gamma (s+\\frac{1}{2})\n/[ \\Gamma (s)^2 \\Gamma (n+s-\\frac{1}{2})\\Gamma (n+s+\\frac{1}{2}) ].  (3)\n\nHypothesis (II) says E_n/O_n\\to 1, so, letting n\\to \\infty  and noting  \n lim_{n\\to \\infty } \\Gamma (n+s)^2 /[\\Gamma (n+s-\\frac{1}{2})\\Gamma (n+s+\\frac{1}{2})]=1,  \nwe obtain  \n\n a_0^2 = \\beta \\cdot \\Gamma (s)^2 /[ \\Gamma (s-\\frac{1}{2})\\Gamma (s+\\frac{1}{2}) ].  (4)\n\nNow use the Euler shift \\Gamma (z+1)=z\\Gamma (z) with z=s-\\frac{1}{2}:\n\n \\Gamma (s+\\frac{1}{2})= (s-\\frac{1}{2})\\Gamma (s-\\frac{1}{2})= (\\beta /2) \\Gamma (s-\\frac{1}{2}).\n\nInsert this into (4):\n\n a_0^2 = \\beta \\cdot \\Gamma (s)^2 /( \\Gamma (s-\\frac{1}{2})\\cdot (\\beta /2)\\Gamma (s-\\frac{1}{2}) )\n      = 2\\cdot [ \\Gamma (s)/\\Gamma (s-\\frac{1}{2}) ]^2,\n\nwhich is exactly Statement 2.\n\n------------------------------------------------------------------------------------------------------------  \n3.  Square-root law  \nWe treat even and odd indices separately.\n\n3.1  Even indices.  \nFrom (2a) and Stirling's expansion  \n\n \\Gamma (N+\\alpha )/\\Gamma (N+\\beta )\n   = N^{\\alpha -\\beta } (1+\\sum _{k\\geq 1} C_k(\\alpha ,\\beta )/N^{k}),  (5)\n\nwhere C_k is a polynomial of degree k in \\alpha ,\\beta , we find for large n  \n\n E_n = a_0\\cdot \\Gamma (s-\\frac{1}{2})/\\Gamma (s)\\cdot n^{\\frac{1}{2}}\\cdot (1+C_1/(2n)+O(n^{-2})). (6)\n\nBecause of (2) we have a_0\\cdot \\Gamma (s-\\frac{1}{2})/\\Gamma (s)=\\sqrt{2}, hence  \n\n E_n = \\sqrt{2n}\\cdot (1+O(n^{-1})).  (7)\n\n3.2  Odd indices.  \nA parallel computation with (2b) gives  \n\n O_n = \\sqrt{2n+1}\\cdot (1+O(n^{-1})) = \\sqrt{2n}\\cdot (1+O(n^{-1})). (8)\n\n3.3  Conclusion.  \nSince a_{2n}=E_n and a_{2n+1}=O_n, (7)-(8) imply  \n\n lim_{n\\to \\infty } a_n/\\sqrt{n} = 1,\n\nestablishing Statement 1.\n\n------------------------------------------------------------------------------------------------------------  \n4.  Complete asymptotic expansion  \n\n4.1  Logarithmic form.  \nWrite n=2N or n=2N+1 and keep s=(\\beta +1)/2.  From (2a)-(2b) and the\nclassical asymptotic series for log \\Gamma  we obtain  \n\n log(a_n/\\sqrt{n})=\\sum _{k\\geq 1} A_k(\\beta )/n^{k},  (9)\n\nwhere A_k is a polynomial in \\beta  of degree k.  A straightforward (though\nlengthy) coefficient comparison yields  \n\n A_1=(\\beta -\\frac{1}{2})/2, A_2=\\beta (1-\\beta )/4, A_3=(4\\beta ^3-6\\beta ^2+1)/24. (10)\n\n4.2  Passage to the a_n-expansion.  \nExponentiating (9) and using the exponential Bell polynomials gives  \n\n a_n = \\sqrt{n}\\cdot (1+\\sum _{k=1}^{m}P_k(\\beta )/n^{k})+O(n^{-m-\\frac{1}{2}}), (11)\n\nwhere  \n\n P_1=A_1, P_2=A_2+A_1^2/2, P_3=A_3+A_1A_2+A_1^3/6, \\ldots  .  \n\nFrom (10) we recover  \n\n P_1(\\beta )=\\beta /2-1/4, P_2(\\beta )=(-4\\beta ^2+4\\beta +1)/32,\n\nmatching Statement 3.  Because the A_k ultimately stem from the\nStirling series, they can be written in closed form via the Bernoulli\nnumbers B_{2j}; the same is therefore true of the P_k, completing the\nproof.\n\n------------------------------------------------------------------------------------------------------------",
      "metadata": {
        "replaced_from": "harder_variant",
        "replacement_date": "2025-07-14T19:09:31.586185",
        "was_fixed": false,
        "difficulty_analysis": "• Variable parameter β.  The original problem deals with the single concrete recurrence aₙ aₙ₊₁ = n+1; here the constant term n+β is left arbitrary, forcing the solver to carry β through every calculation and to master Γ-function identities with symbolic parameters.\n\n• Advanced special-function techniques.  Determining a₀ now requires evaluating an infinite product that no longer collapses to the classical Wallis product; one must manipulate Euler products, use the Gamma duplication formula and Stirling’s asymptotics.\n\n• Higher-order asymptotics.  Beyond the classical √n-law, the problem demands a full asymptotic expansion with explicit coefficients expressed via Bernoulli numbers, something completely absent from the original statement.\n\n• Multiple interacting concepts.  The solution intertwines discrete recurrences, infinite products, special-function theory (Γ, duplication), real analysis (convergence of products and series), and asymptotic analysis (Euler–Maclaurin).\n\n• Substantially longer argument.  Each of the three parts requires a separate, non-trivial chain of reasoning; together they are markedly more intricate than proving π a₀²=2."
      }
    },
    "original_kernel_variant": {
      "question": "Fix a real parameter \\beta  > 0 and let (a_n)_{n\\geq 0} be a sequence of positive real numbers satisfying  \n\n (I) a_n a_{n+1} = n + \\beta    (n = 0,1,2,\\ldots ),  \n\n (II) lim_{n\\to \\infty } a_n / a_{n+1} = 1.  \n\nProve the following assertions.\n\n1.  (Square-root law) lim_{n\\to \\infty } a_n / \\sqrt{n} = 1.  \n\n2.  (Exact normalisation)   \n  a_0^2 = 2\\cdot [ \\Gamma ((\\beta +1)/2) / \\Gamma (\\beta /2) ]^2.  \n\n3.  (Full asymptotic expansion) For every m\\in \\mathbb{N} there exist polynomials P_1,\\ldots ,P_m in \\beta  with deg P_k = k such that  \n\n  a_n = \\sqrt{n} \\cdot  ( 1 + \\sum _{k=1}^{m} P_k(\\beta )/n^{k} ) + O(n^{-m-\\frac{1}{2}})  (n\\to \\infty ).  \n\n The first two polynomials are  \n  P_1(\\beta ) = \\beta /2 - 1/4,  P_2(\\beta ) = (-4\\beta ^2 + 4\\beta  + 1) / 32,  \n\n and in particular  \n\n  lim_{n\\to \\infty } n ( a_n - \\sqrt{n} ) = \\beta /2 - 1/4.\n\n(The general coefficients can be written explicitly in terms of Bernoulli numbers.)\n\n------------------------------------------------------------------------------------------------------------",
      "solution": "Throughout we fix \\beta  > 0 and assume a_n > 0.  We denote n\\to \\infty  with n\\in \\mathbb{N}.\n\n0.  Even-odd splitting  \nDefine  \n\n E_n := a_{2n},  O_n := a_{2n+1}  (n\\geq 0).\n\nFrom (I) we derive  \n\n E_nO_n = 2n+\\beta ,  O_nE_{n+1} = 2n+1+\\beta .  (\\dagger )\n\nConsequently  \n\n E_{n+1} = (2n+1+\\beta )/O_n,  O_n = (2n+\\beta )/E_n.  (\\dagger \\dagger )\n\n------------------------------------------------------------------------------------------------------------  \n1.  Closed product formulae  \nIterating (\\dagger \\dagger ) yields  \n\n E_n = a_0 \\cdot  \\prod _{j=1}^{n} (2j-1+\\beta )/(2j-2+\\beta ),  (1a)  \n\n O_n = (\\beta /a_0)\\cdot \\prod _{j=1}^{n} (2j+\\beta )/(2j-1+\\beta ).  (1b)\n\n(The case n=0 reads a_1=\\beta /a_0.)\n\n------------------------------------------------------------------------------------------------------------  \n2.  Determination of a_0  \nLet  \n\n s := (\\beta +1)/2  (so \\beta =2s-1 and s>\\frac{1}{2}).\n\nUsing the identity  \n  \\prod _{j=1}^{n}(j+\\alpha )=\\Gamma (n+1+\\alpha )/\\Gamma (1+\\alpha ),  \nformulae (1a)-(1b) become  \n\n E_n = a_0\\cdot \\Gamma (n+s)/\\Gamma (s)\\cdot \\Gamma (s-\\frac{1}{2})/\\Gamma (n+s-\\frac{1}{2}),  (2a)  \n\n O_n = (\\beta /a_0)\\cdot \\Gamma (n+s+\\frac{1}{2})/\\Gamma (s+\\frac{1}{2})\\cdot \\Gamma (s)/\\Gamma (n+s).  (2b)\n\nTaking the quotient we get  \n\n E_n/O_n = (a_0^2/\\beta ) \\cdot  \\Gamma (n+s)^2 \\Gamma (s-\\frac{1}{2})\\Gamma (s+\\frac{1}{2})\n/[ \\Gamma (s)^2 \\Gamma (n+s-\\frac{1}{2})\\Gamma (n+s+\\frac{1}{2}) ].  (3)\n\nHypothesis (II) says E_n/O_n\\to 1, so, letting n\\to \\infty  and noting  \n lim_{n\\to \\infty } \\Gamma (n+s)^2 /[\\Gamma (n+s-\\frac{1}{2})\\Gamma (n+s+\\frac{1}{2})]=1,  \nwe obtain  \n\n a_0^2 = \\beta \\cdot \\Gamma (s)^2 /[ \\Gamma (s-\\frac{1}{2})\\Gamma (s+\\frac{1}{2}) ].  (4)\n\nNow use the Euler shift \\Gamma (z+1)=z\\Gamma (z) with z=s-\\frac{1}{2}:\n\n \\Gamma (s+\\frac{1}{2})= (s-\\frac{1}{2})\\Gamma (s-\\frac{1}{2})= (\\beta /2) \\Gamma (s-\\frac{1}{2}).\n\nInsert this into (4):\n\n a_0^2 = \\beta \\cdot \\Gamma (s)^2 /( \\Gamma (s-\\frac{1}{2})\\cdot (\\beta /2)\\Gamma (s-\\frac{1}{2}) )\n      = 2\\cdot [ \\Gamma (s)/\\Gamma (s-\\frac{1}{2}) ]^2,\n\nwhich is exactly Statement 2.\n\n------------------------------------------------------------------------------------------------------------  \n3.  Square-root law  \nWe treat even and odd indices separately.\n\n3.1  Even indices.  \nFrom (2a) and Stirling's expansion  \n\n \\Gamma (N+\\alpha )/\\Gamma (N+\\beta )\n   = N^{\\alpha -\\beta } (1+\\sum _{k\\geq 1} C_k(\\alpha ,\\beta )/N^{k}),  (5)\n\nwhere C_k is a polynomial of degree k in \\alpha ,\\beta , we find for large n  \n\n E_n = a_0\\cdot \\Gamma (s-\\frac{1}{2})/\\Gamma (s)\\cdot n^{\\frac{1}{2}}\\cdot (1+C_1/(2n)+O(n^{-2})). (6)\n\nBecause of (2) we have a_0\\cdot \\Gamma (s-\\frac{1}{2})/\\Gamma (s)=\\sqrt{2}, hence  \n\n E_n = \\sqrt{2n}\\cdot (1+O(n^{-1})).  (7)\n\n3.2  Odd indices.  \nA parallel computation with (2b) gives  \n\n O_n = \\sqrt{2n+1}\\cdot (1+O(n^{-1})) = \\sqrt{2n}\\cdot (1+O(n^{-1})). (8)\n\n3.3  Conclusion.  \nSince a_{2n}=E_n and a_{2n+1}=O_n, (7)-(8) imply  \n\n lim_{n\\to \\infty } a_n/\\sqrt{n} = 1,\n\nestablishing Statement 1.\n\n------------------------------------------------------------------------------------------------------------  \n4.  Complete asymptotic expansion  \n\n4.1  Logarithmic form.  \nWrite n=2N or n=2N+1 and keep s=(\\beta +1)/2.  From (2a)-(2b) and the\nclassical asymptotic series for log \\Gamma  we obtain  \n\n log(a_n/\\sqrt{n})=\\sum _{k\\geq 1} A_k(\\beta )/n^{k},  (9)\n\nwhere A_k is a polynomial in \\beta  of degree k.  A straightforward (though\nlengthy) coefficient comparison yields  \n\n A_1=(\\beta -\\frac{1}{2})/2, A_2=\\beta (1-\\beta )/4, A_3=(4\\beta ^3-6\\beta ^2+1)/24. (10)\n\n4.2  Passage to the a_n-expansion.  \nExponentiating (9) and using the exponential Bell polynomials gives  \n\n a_n = \\sqrt{n}\\cdot (1+\\sum _{k=1}^{m}P_k(\\beta )/n^{k})+O(n^{-m-\\frac{1}{2}}), (11)\n\nwhere  \n\n P_1=A_1, P_2=A_2+A_1^2/2, P_3=A_3+A_1A_2+A_1^3/6, \\ldots  .  \n\nFrom (10) we recover  \n\n P_1(\\beta )=\\beta /2-1/4, P_2(\\beta )=(-4\\beta ^2+4\\beta +1)/32,\n\nmatching Statement 3.  Because the A_k ultimately stem from the\nStirling series, they can be written in closed form via the Bernoulli\nnumbers B_{2j}; the same is therefore true of the P_k, completing the\nproof.\n\n------------------------------------------------------------------------------------------------------------",
      "metadata": {
        "replaced_from": "harder_variant",
        "replacement_date": "2025-07-14T01:37:45.471600",
        "was_fixed": false,
        "difficulty_analysis": "• Variable parameter β.  The original problem deals with the single concrete recurrence aₙ aₙ₊₁ = n+1; here the constant term n+β is left arbitrary, forcing the solver to carry β through every calculation and to master Γ-function identities with symbolic parameters.\n\n• Advanced special-function techniques.  Determining a₀ now requires evaluating an infinite product that no longer collapses to the classical Wallis product; one must manipulate Euler products, use the Gamma duplication formula and Stirling’s asymptotics.\n\n• Higher-order asymptotics.  Beyond the classical √n-law, the problem demands a full asymptotic expansion with explicit coefficients expressed via Bernoulli numbers, something completely absent from the original statement.\n\n• Multiple interacting concepts.  The solution intertwines discrete recurrences, infinite products, special-function theory (Γ, duplication), real analysis (convergence of products and series), and asymptotic analysis (Euler–Maclaurin).\n\n• Substantially longer argument.  Each of the three parts requires a separate, non-trivial chain of reasoning; together they are markedly more intricate than proving π a₀²=2."
      }
    }
  },
  "checked": true,
  "problem_type": "proof"
}